README.rst
setup.py
setupbox/SClient.py
setupbox/__init__.py
setupbox/client_init.py
setupbox/db.py
setupbox/fs.py
setupbox/git_wrapper.py
setupbox/sb_wrapper.py
setupbox/svn_wrapper.py
setupbox/transaction_manager.py
setupbox/vcs.py
setupbox.egg-info/PKG-INFO
setupbox.egg-info/SOURCES.txt
setupbox.egg-info/dependency_links.txt
setupbox.egg-info/not-zip-safe
setupbox.egg-info/top_level.txt