Metadata-Version: 1.0
Name: setupbox
Version: 1.0
Summary: Middleware for implementing own storage cloud
Home-page: http://maxtortime.github.io/SetupBox
Author: Taehwan Kim
Author-email: maxtortime@gmail.com
License: GPLv2
Platform: UNKNOWN
